autochord/__init__.py
autochord/res/nnls-chroma.so
autochord-0.1.3.dist-info/LICENSE
autochord-0.1.3.dist-info/METADATA
autochord-0.1.3.dist-info/WHEEL
autochord-0.1.3.dist-info/top_level.txt
autochord-0.1.3.dist-info/RECORD
