Metadata-Version: 2.1
Name: autochord
Version: 0.1.3
Summary: Automatic Chord Recognition library
Home-page: https://github.com/cjbayron/autochord
Author: Christopher John Bayron
Author-email: cjdbayron@gmail.com
License: UNKNOWN
Platform: UNKNOWN
Classifier: Programming Language :: Python :: 3
Classifier: License :: OSI Approved :: MIT License
Classifier: Operating System :: OS Independent
Requires-Python: >=3.6
Requires-Dist: gdown
Requires-Dist: numpy
Requires-Dist: scipy
Requires-Dist: librosa
Requires-Dist: vamp
Requires-Dist: lazycats
Requires-Dist: tensorflow (>=2.6)
